fastmcp_agents/library/agent/simple_code/__init__.py
fastmcp_agents/library/agent/simple_code/archive/base.py.disabled
fastmcp_agents/library/agent/simple_code/archive/workspace.py.disabled
fastmcp_agents/library/agent/simple_code/helpers/filesystem.py
fastmcp_agents/library/agent/simple_code/helpers/git.py
fastmcp_agents/library/agent/simple_code/implement.py
fastmcp_agents/library/agent/simple_code/investigate.py
fastmcp_agents_library_agent_simple_code-0.5.8.dist-info/WHEEL
fastmcp_agents_library_agent_simple_code-0.5.8.dist-info/entry_points.txt
fastmcp_agents_library_agent_simple_code-0.5.8.dist-info/METADATA
fastmcp_agents_library_agent_simple_code-0.5.8.dist-info/RECORD
