Metadata-Version: 2.3
Name: fastmcp-agents-library-agent-simple-code
Version: 0.5.8
Summary: Agents for Simple Code
Requires-Dist: fastmcp-ai-agent-bridge-pydantic-ai>=0.1.2
Requires-Dist: gitpython>=3.1.44
Requires-Dist: fastmcp-agents-library-mcp
Requires-Python: >=3.13
